Workbook

Sheet Products
A1: SKU | B1: Product Name | C1: Category | D1: Supplier | E1: Cost Price | F1: Selling Price | G1: Reorder Level
A2: SKU-1001 | B2: Wireless Noise-Canceling Headphones | C2: Electronics | D2: Apex Audio Dist. | E2: 45 | F2: 89.99 | G2: 15
A3: SKU-1002 | B3: Inomical Mechanical Keyboard | C3: Electronics | D3: Apex Audio Dist. | E3: 35 | F3: 69.99 | G3: 10
A4: SKU-1003 | B4: Stainless Steel Insulated Tumbler | C4: Home & Kitchen | D4: Vanguard Goods | E4: 8.5 | F4: 19.99 | G4: 25
A5: SKU-1004 | B5: Ceramic Pour-Over Coffee Dripper | C5: Home & Kitchen | D5: Vanguard Goods | E5: 12 | F5: 24.5 | G5: 15
A6: SKU-1005 | B6: Organic Cotton Heavyweight T-Shirt | C6: Apparel | D6: ThreadCraft Apparel | E6: 9 | F6: 24 | G6: 30
A7: SKU-1006 | B7: Water-Resistant Commuter Backpack | C7: Accessories | D7: Urban Cargo Co. | E7: 28 | F7: 58 | G7: 20
A8: SKU-1007 | B8: Leather Trifold RFID Wallet | C8: Accessories | D8: Urban Cargo Co. | E8: 14 | F8: 32 | G8: 15
A9: SKU-1008 | B9: Smart Fitness Tracker Watch | C9: Electronics | D9: Apex Audio Dist. | E9: 22 | F9: 49.99 | G9: 18
A10: SKU-1009 | B10: Soy Wax Aromatherapy Candle | C10: Home & Kitchen | D10: Aroma Botanics | E10: 6.5 | F10: 16 | G10: 20
A11: SKU-1010 | B11: Merino Wool Everyday Socks (3-Pack) | C11: Apparel | D11: ThreadCraft Apparel | E11: 7.5 | F11: 18.5 | G11: 25

Sheet Inventory
A1: Inventory Health & Real-Time Tracking
B2: Total Inventory Value | D2: Total Units in Stock | F2: Potential Sales Value | H2: Reorder Alerts
B3: =SUM(G6:G15) -> 3760 | D3: =SUM(F6:F15) -> 269 | F3: =SUM(H6:H15) -> 8341.17 | H3: =COUNTIF(I6:I15, "REORDER") -> 4
A5: SKU | B5: Product Name | C5: Category | D5: Initial Stock | E5: Units Sold | F5: Current Stock | G5: Total Cost Value | H5: Retail Value | I5: Stock Status
A6: SKU-1001 | B6: =VLOOKUP(A6, Products!$A$2:$G$11, 2, FALSE) -> Wireless Noise-Canceling Headphones | C6: =VLOOKUP(A6, Products!$A$2:$G$11, 3, FALSE) -> Electronics | D6: 50 | E6: =SUMIF(Sales!$B$2:$B$100, A6, Sales!$E$2:$E$100) -> 38 | F6: =D6-E6 -> 12 | G6: =F6*VLOOKUP(A6, Products!$A$2:$G$11, 5, FALSE) -> 540 | H6: =F6*VLOOKUP(A6, Products!$A$2:$G$11, 6, FALSE) -> 1079.88 | I6: =IF(F6<=0, "OUT OF STOCK", IF(F6<=VLOOKUP(A6, Products!$A$2:$G$11, 7, FALSE), "REORDER", "IN STOCK")) -> REORDER
A7: SKU-1002 | B7: =VLOOKUP(A7, Products!$A$2:$G$11, 2, FALSE) -> Inomical Mechanical Keyboard | C7: =VLOOKUP(A7, Products!$A$2:$G$11, 3, FALSE) -> Electronics | D7: 30 | E7: =SUMIF(Sales!$B$2:$B$100, A7, Sales!$E$2:$E$100) -> 22 | F7: =D7-E7 -> 8 | G7: =F7*VLOOKUP(A7, Products!$A$2:$G$11, 5, FALSE) -> 280 | H7: =F7*VLOOKUP(A7, Products!$A$2:$G$11, 6, FALSE) -> 559.92 | I7: =IF(F7<=0, "OUT OF STOCK", IF(F7<=VLOOKUP(A7, Products!$A$2:$G$11, 7, FALSE), "REORDER", "IN STOCK")) -> REORDER
A8: SKU-1003 | B8: =VLOOKUP(A8, Products!$A$2:$G$11, 2, FALSE) -> Stainless Steel Insulated Tumbler | C8: =VLOOKUP(A8, Products!$A$2:$G$11, 3, FALSE) -> Home & Kitchen | D8: 60 | E8: =SUMIF(Sales!$B$2:$B$100, A8, Sales!$E$2:$E$100) -> 12 | F8: =D8-E8 -> 48 | G8: =F8*VLOOKUP(A8, Products!$A$2:$G$11, 5, FALSE) -> 408 | H8: =F8*VLOOKUP(A8, Products!$A$2:$G$11, 6, FALSE) -> 959.52 | I8: =IF(F8<=0, "OUT OF STOCK", IF(F8<=VLOOKUP(A8, Products!$A$2:$G$11, 7, FALSE), "REORDER", "IN STOCK")) -> IN STOCK
A9: SKU-1004 | B9: =VLOOKUP(A9, Products!$A$2:$G$11, 2, FALSE) -> Ceramic Pour-Over Coffee Dripper | C9: =VLOOKUP(A9, Products!$A$2:$G$11, 3, FALSE) -> Home & Kitchen | D9: 40 | E9: =SUMIF(Sales!$B$2:$B$100, A9, Sales!$E$2:$E$100) -> 10 | F9: =D9-E9 -> 30 | G9: =F9*VLOOKUP(A9, Products!$A$2:$G$11, 5, FALSE) -> 360 | H9: =F9*VLOOKUP(A9, Products!$A$2:$G$11, 6, FALSE) -> 735 | I9: =IF(F9<=0, "OUT OF STOCK", IF(F9<=VLOOKUP(A9, Products!$A$2:$G$11, 7, FALSE), "REORDER", "IN STOCK")) -> IN STOCK
A10: SKU-1005 | B10: =VLOOKUP(A10, Products!$A$2:$G$11, 2, FALSE) -> Organic Cotton Heavyweight T-Shirt | C10: =VLOOKUP(A10, Products!$A$2:$G$11, 3, FALSE) -> Apparel | D10: 80 | E10: =SUMIF(Sales!$B$2:$B$100, A10, Sales!$E$2:$E$100) -> 55 | F10: =D10-E10 -> 25 | G10: =F10*VLOOKUP(A10, Products!$A$2:$G$11, 5, FALSE) -> 225 | H10: =F10*VLOOKUP(A10, Products!$A$2:$G$11, 6, FALSE) -> 600 | I10: =IF(F10<=0, "OUT OF STOCK", IF(F10<=VLOOKUP(A10, Products!$A$2:$G$11, 7, FALSE), "REORDER", "IN STOCK")) -> REORDER
A11: SKU-1006 | B11: =VLOOKUP(A11, Products!$A$2:$G$11, 2, FALSE) -> Water-Resistant Commuter Backpack | C11: =VLOOKUP(A11, Products!$A$2:$G$11, 3, FALSE) -> Accessories | D11: 35 | E11: =SUMIF(Sales!$B$2:$B$100, A11, Sales!$E$2:$E$100) -> 12 | F11: =D11-E11 -> 23 | G11: =F11*VLOOKUP(A11, Products!$A$2:$G$11, 5, FALSE) -> 644 | H11: =F11*VLOOKUP(A11, Products!$A$2:$G$11, 6, FALSE) -> 1334 | I11: =IF(F11<=0, "OUT OF STOCK", IF(F11<=VLOOKUP(A11, Products!$A$2:$G$11, 7, FALSE), "REORDER", "IN STOCK")) -> IN STOCK
A12: SKU-1007 | B12: =VLOOKUP(A12, Products!$A$2:$G$11, 2, FALSE) -> Leather Trifold RFID Wallet | C12: =VLOOKUP(A12, Products!$A$2:$G$11, 3, FALSE) -> Accessories | D12: 45 | E12: =SUMIF(Sales!$B$2:$B$100, A12, Sales!$E$2:$E$100) -> 15 | F12: =D12-E12 -> 30 | G12: =F12*VLOOKUP(A12, Products!$A$2:$G$11, 5, FALSE) -> 420 | H12: =F12*VLOOKUP(A12, Products!$A$2:$G$11, 6, FALSE) -> 960 | I12: =IF(F12<=0, "OUT OF STOCK", IF(F12<=VLOOKUP(A12, Products!$A$2:$G$11, 7, FALSE), "REORDER", "IN STOCK")) -> IN STOCK
A13: SKU-1008 | B13: =VLOOKUP(A13, Products!$A$2:$G$11, 2, FALSE) -> Smart Fitness Tracker Watch | C13: =VLOOKUP(A13, Products!$A$2:$G$11, 3, FALSE) -> Electronics | D13: 25 | E13: =SUMIF(Sales!$B$2:$B$100, A13, Sales!$E$2:$E$100) -> 10 | F13: =D13-E13 -> 15 | G13: =F13*VLOOKUP(A13, Products!$A$2:$G$11, 5, FALSE) -> 330 | H13: =F13*VLOOKUP(A13, Products!$A$2:$G$11, 6, FALSE) -> 749.85 | I13: =IF(F13<=0, "OUT OF STOCK", IF(F13<=VLOOKUP(A13, Products!$A$2:$G$11, 7, FALSE), "REORDER", "IN STOCK")) -> REORDER
A14: SKU-1009 | B14: =VLOOKUP(A14, Products!$A$2:$G$11, 2, FALSE) -> Soy Wax Aromatherapy Candle | C14: =VLOOKUP(A14, Products!$A$2:$G$11, 3, FALSE) -> Home & Kitchen | D14: 50 | E14: =SUMIF(Sales!$B$2:$B$100, A14, Sales!$E$2:$E$100) -> 18 | F14: =D14-E14 -> 32 | G14: =F14*VLOOKUP(A14, Products!$A$2:$G$11, 5, FALSE) -> 208 | H14: =F14*VLOOKUP(A14, Products!$A$2:$G$11, 6, FALSE) -> 512 | I14: =IF(F14<=0, "OUT OF STOCK", IF(F14<=VLOOKUP(A14, Products!$A$2:$G$11, 7, FALSE), "REORDER", "IN STOCK")) -> IN STOCK
A15: SKU-1010 | B15: =VLOOKUP(A15, Products!$A$2:$G$11, 2, FALSE) -> Merino Wool Everyday Socks (3-Pack) | C15: =VLOOKUP(A15, Products!$A$2:$G$11, 3, FALSE) -> Apparel | D15: 70 | E15: =SUMIF(Sales!$B$2:$B$100, A15, Sales!$E$2:$E$100) -> 24 | F15: =D15-E15 -> 46 | G15: =F15*VLOOKUP(A15, Products!$A$2:$G$11, 5, FALSE) -> 345 | H15: =F15*VLOOKUP(A15, Products!$A$2:$G$11, 6, FALSE) -> 851 | I15: =IF(F15<=0, "OUT OF STOCK", IF(F15<=VLOOKUP(A15, Products!$A$2:$G$11, 7, FALSE), "REORDER", "IN STOCK")) -> IN STOCK
A16: Total | D16: =SUM(D6:D15) -> 485 | E16: =SUM(E6:E15) -> 216 | F16: =SUM(F6:F15) -> 269 | G16: =SUM(G6:G15) -> 3760 | H16: =SUM(H6:H15) -> 8341.17

Sheet Sales
A1: Transaction ID | B1: SKU | C1: Product Name | D1: Date | E1: Quantity Sold | F1: Unit Price | G1: Total Revenue | H1: Payment Method
A2: TXN-2026-001 | B2: SKU-1001 | C2: =IFERROR(VLOOKUP(B2, Products!$A$2:$G$11, 2, FALSE), "") -> Wireless Noise-Canceling Headphones | D2: 46280 | E2: 20 | F2: =IFERROR(VLOOKUP(B2, Products!$A$2:$G$11, 6, FALSE), "") -> 89.99 | G2: =IF(OR(ISBLANK(E2), ISBLANK(F2)), "", E2*F2) -> 1799.8 | H2: Credit Card
A3: TXN-2026-002 | B3: SKU-1005 | C3: =IFERROR(VLOOKUP(B3, Products!$A$2:$G$11, 2, FALSE), "") -> Organic Cotton Heavyweight T-Shirt | D3: 46280 | E3: 30 | F3: =IFERROR(VLOOKUP(B3, Products!$A$2:$G$11, 6, FALSE), "") -> 24 | G3: =IF(OR(ISBLANK(E3), ISBLANK(F3)), "", E3*F3) -> 720 | H3: Online / UPI
A4: TXN-2026-003 | B4: SKU-1003 | C4: =IFERROR(VLOOKUP(B4, Products!$A$2:$G$11, 2, FALSE), "") -> Stainless Steel Insulated Tumbler | D4: 46281 | E4: 12 | F4: =IFERROR(VLOOKUP(B4, Products!$A$2:$G$11, 6, FALSE), "") -> 19.99 | G4: =IF(OR(ISBLANK(E4), ISBLANK(F4)), "", E4*F4) -> 239.88 | H4: Cash
A5: TXN-2026-004 | B5: SKU-1002 | C5: =IFERROR(VLOOKUP(B5, Products!$A$2:$G$11, 2, FALSE), "") -> Inomical Mechanical Keyboard | D5: 46281 | E5: 14 | F5: =IFERROR(VLOOKUP(B5, Products!$A$2:$G$11, 6, FALSE), "") -> 69.99 | G5: =IF(OR(ISBLANK(E5), ISBLANK(F5)), "", E5*F5) -> 979.86 | H5: Credit Card
A6: TXN-2026-005 | B6: SKU-1008 | C6: =IFERROR(VLOOKUP(B6, Products!$A$2:$G$11, 2, FALSE), "") -> Smart Fitness Tracker Watch | D6: 46282 | E6: 6 | F6: =IFERROR(VLOOKUP(B6, Products!$A$2:$G$11, 6, FALSE), "") -> 49.99 | G6: =IF(OR(ISBLANK(E6), ISBLANK(F6)), "", E6*F6) -> 299.94 | H6: Debit Card
A7: TXN-2026-006 | B7: SKU-1001 | C7: =IFERROR(VLOOKUP(B7, Products!$A$2:$G$11, 2, FALSE), "") -> Wireless Noise-Canceling Headphones | D7: 46283 | E7: 18 | F7: =IFERROR(VLOOKUP(B7, Products!$A$2:$G$11, 6, FALSE), "") -> 89.99 | G7: =IF(OR(ISBLANK(E7), ISBLANK(F7)), "", E7*F7) -> 1619.82 | H7: Credit Card
A8: TXN-2026-007 | B8: SKU-1006 | C8: =IFERROR(VLOOKUP(B8, Products!$A$2:$G$11, 2, FALSE), "") -> Water-Resistant Commuter Backpack | D8: 46283 | E8: 12 | F8: =IFERROR(VLOOKUP(B8, Products!$A$2:$G$11, 6, FALSE), "") -> 58 | G8: =IF(OR(ISBLANK(E8), ISBLANK(F8)), "", E8*F8) -> 696 | H8: Online / UPI
A9: TXN-2026-008 | B9: SKU-1005 | C9: =IFERROR(VLOOKUP(B9, Products!$A$2:$G$11, 2, FALSE), "") -> Organic Cotton Heavyweight T-Shirt | D9: 46284 | E9: 25 | F9: =IFERROR(VLOOKUP(B9, Products!$A$2:$G$11, 6, FALSE), "") -> 24 | G9: =IF(OR(ISBLANK(E9), ISBLANK(F9)), "", E9*F9) -> 600 | H9: Cash
A10: TXN-2026-009 | B10: SKU-1004 | C10: =IFERROR(VLOOKUP(B10, Products!$A$2:$G$11, 2, FALSE), "") -> Ceramic Pour-Over Coffee Dripper | D10: 46285 | E10: 10 | F10: =IFERROR(VLOOKUP(B10, Products!$A$2:$G$11, 6, FALSE), "") -> 24.5 | G10: =IF(OR(ISBLANK(E10), ISBLANK(F10)), "", E10*F10) -> 245 | H10: Credit Card
A11: TXN-2026-010 | B11: SKU-1002 | C11: =IFERROR(VLOOKUP(B11, Products!$A$2:$G$11, 2, FALSE), "") -> Inomical Mechanical Keyboard | D11: 46286 | E11: 8 | F11: =IFERROR(VLOOKUP(B11, Products!$A$2:$G$11, 6, FALSE), "") -> 69.99 | G11: =IF(OR(ISBLANK(E11), ISBLANK(F11)), "", E11*F11) -> 559.92 | H11: Online / UPI
A12: TXN-2026-011 | B12: SKU-1007 | C12: =IFERROR(VLOOKUP(B12, Products!$A$2:$G$11, 2, FALSE), "") -> Leather Trifold RFID Wallet | D12: 46286 | E12: 15 | F12: =IFERROR(VLOOKUP(B12, Products!$A$2:$G$11, 6, FALSE), "") -> 32 | G12: =IF(OR(ISBLANK(E12), ISBLANK(F12)), "", E12*F12) -> 480 | H12: Credit Card
A13: TXN-2026-012 | B13: SKU-1009 | C13: =IFERROR(VLOOKUP(B13, Products!$A$2:$G$11, 2, FALSE), "") -> Soy Wax Aromatherapy Candle | D13: 46287 | E13: 18 | F13: =IFERROR(VLOOKUP(B13, Products!$A$2:$G$11, 6, FALSE), "") -> 16 | G13: =IF(OR(ISBLANK(E13), ISBLANK(F13)), "", E13*F13) -> 288 | H13: Cash
... A15: TXN-2026-014 | B15: SKU-1008 | C15: =IFERROR(VLOOKUP(B15, Products!$A$2:$G$11, 2, FALSE), "") -> Smart Fitness Tracker Watch | D15: 46288 | E15: 4 | F15: =IFERROR(VLOOKUP(B15, Products!$A$2:$G$11, 6, FALSE), "") -> 49.99 | G15: =IF(OR(ISBLANK(E15), ISBLANK(F15)), "", E15*F15) -> 199.96 | H15: Credit Card
A16: Total | E16: =SUM(E2:E15) -> 216 | G16: =SUM(G2:G15) -> 9172.18
